ewoks/__init__.py
ewoks/__main__.py
ewoks/_engines.py
ewoks/bindings.py
ewoks/errors.py
ewoks/graph_cache.py
ewoks/utils.py
ewoks/_requirements/__init__.py
ewoks/_requirements/pip/__init__.py
ewoks/_requirements/pip/extract.py
ewoks/_requirements/pip/install.py
ewoks/_requirements/pip/sanitize.py
ewoks/cli_utils/__init__.py
ewoks/cli_utils/cli_convert_utils.py
ewoks/cli_utils/cli_install_utils.py
ewoks/cli_utils/cli_parse.py
ewoks/cli_utils/cli_show_utils.py
ewoks/tests/__init__.py
ewoks/tests/conftest.py
ewoks/tests/test_cli.py
ewoks/tests/test_convert_cli.py
ewoks/tests/test_engines.py
ewoks/tests/test_execute_cli.py
ewoks/tests/test_icat.py
ewoks/tests/test_install_cli.py
ewoks/tests/test_notebooks.py
ewoks/tests/test_projects.py
ewoks/tests/test_requirements.py
ewoks/tests/test_show_cli.py
ewoks/tests/utils.py
ewoks/tests/notebooks/__init__.py
ewoks/tests/notebooks/benchmark.ipynb
ewoks/tests/notebooks/running_workflows.ipynb
ewoks-4.0.0.dist-info/licenses/LICENSE.md
ewoks-4.0.0.dist-info/METADATA
ewoks-4.0.0.dist-info/WHEEL
ewoks-4.0.0.dist-info/entry_points.txt
ewoks-4.0.0.dist-info/top_level.txt
ewoks-4.0.0.dist-info/RECORD
