Metadata-Version: 2.4
Name: ewoks
Version: 4.0.0
Summary: Extensible Workflow System
Author-email: ESRF <dau-pydev@esrf.fr>
License: # MIT License
Project-URL: Homepage, https://gitlab.esrf.fr/workflow/ewoks/ewoks/
Project-URL: Documentation, https://ewoks.readthedocs.io/
Project-URL: Repository, https://gitlab.esrf.fr/workflow/ewoks/ewoks/
Project-URL: Issues, https://gitlab.esrf.fr/workflow/ewoks/ewoks/issues
Project-URL: Changelog, https://gitlab.esrf.fr/workflow/ewoks/ewoks/-/blob/main/CHANGELOG.md
Classifier: Intended Audience :: Science/Research
Classifier: License :: OSI Approved :: MIT License
Classifier: Programming Language :: Python :: 3
Requires-Python: >=3.8
License-File: LICENSE.md
Requires-Dist: ewokscore<5,>=4.0.1
Requires-Dist: ewoksutils<2,>=1.6.0
Requires-Dist: tabulate
Requires-Dist: importlib_resources; python_version < "3.9"
Provides-Extra: dask
Requires-Dist: ewoksdask<3,>=2; extra == "dask"
Provides-Extra: ppf
Requires-Dist: ewoksppf<3,>=2; extra == "ppf"
Provides-Extra: orange
Requires-Dist: ewoksorange<4,>=3; extra == "orange"
Provides-Extra: esrf-data-portal
Requires-Dist: pyicat-plus; extra == "esrf-data-portal"
Provides-Extra: notebooks
Requires-Dist: ewokscore[notebooks]; extra == "notebooks"
Provides-Extra: test
Requires-Dist: ewoksutils[test]; extra == "test"
Requires-Dist: ewoks[dask]; extra == "test"
Requires-Dist: ewoks[ppf]; extra == "test"
Requires-Dist: ewoks[orange]; extra == "test"
Requires-Dist: ewoks[esrf-data-portal]; extra == "test"
Requires-Dist: pytest>=7; extra == "test"
Requires-Dist: testbook; extra == "test"
Requires-Dist: ipykernel; extra == "test"
Requires-Dist: importlib_resources; extra == "test"
Requires-Dist: pyqt5; extra == "test"
Requires-Dist: pytest-venv; extra == "test"
Provides-Extra: dev
Requires-Dist: ewoks[test]; extra == "dev"
Requires-Dist: black[jupyter]>=25; extra == "dev"
Requires-Dist: flake8>=4; extra == "dev"
Requires-Dist: flake8_nb>=0.3.1; extra == "dev"
Requires-Dist: isort; extra == "dev"
Provides-Extra: doc
Requires-Dist: ewoks[test]; extra == "doc"
Requires-Dist: sphinx>=4.5; extra == "doc"
Requires-Dist: sphinx-autodoc-typehints>=1.16; extra == "doc"
Requires-Dist: ipykernel; extra == "doc"
Requires-Dist: nbsphinx; extra == "doc"
Requires-Dist: nbsphinx_link; extra == "doc"
Requires-Dist: pydata-sphinx-theme; extra == "doc"
Requires-Dist: sphinx-argparse; extra == "doc"
Requires-Dist: sphinx-copybutton; extra == "doc"
Dynamic: license-file
